tws_integrated_functions/__init__.py
tws_integrated_functions/account_summary.py
tws_integrated_functions/appConnectionTws.py
tws_integrated_functions/contract_charact.py
tws_integrated_functions/market_reader.py
tws_integrated_functions/submit_order.py
ConnTwsFunctions_projectX_IbTws-0.0.4.dist-info/LICENSE
ConnTwsFunctions_projectX_IbTws-0.0.4.dist-info/METADATA
ConnTwsFunctions_projectX_IbTws-0.0.4.dist-info/WHEEL
ConnTwsFunctions_projectX_IbTws-0.0.4.dist-info/top_level.txt
ConnTwsFunctions_projectX_IbTws-0.0.4.dist-info/RECORD
