Metadata-Version: 2.1
Name: ConnTwsFunctions-projectX-IbTws
Version: 0.0.4
Summary: A package with Tws functions
Home-page: https://github.com/ProjectIbX/ConnTwsFunctions
Author: ProjectX Authors
Author-email: nikolay.gyuneliev@gmail.com
License: UNKNOWN
Project-URL: Bug Tracker, https://github.com/ProjectIbX/ConnTwsFunctions/src
Platform: UNKNOWN
Classifier: Programming Language :: Python :: 3
Classifier: License :: OSI Approved :: MIT License
Classifier: Operating System :: OS Independent
Requires-Python: >=3.8
License-File: LICENSE
